WS2801_RPI.py
WS2801_RPI-1.0.0.dev4.dist-info/DESCRIPTION.rst
WS2801_RPI-1.0.0.dev4.dist-info/METADATA
WS2801_RPI-1.0.0.dev4.dist-info/RECORD
WS2801_RPI-1.0.0.dev4.dist-info/WHEEL
WS2801_RPI-1.0.0.dev4.dist-info/metadata.json
WS2801_RPI-1.0.0.dev4.dist-info/top_level.txt
