Metadata-Version: 2.0
Name: WS2801-RPI
Version: 1.0.0.dev4
Summary: Conecting WS2801 LED strip to Raspberry Pi
Home-page: https://github.com/mk2366/WS2801python_rpi
Author: Markus Kupke
Author-email: kupkemarkus@gmail.com
License: GNU GENERAL PUBLIC LICENSE
Keywords: RaspberryPi WS2801
Platform: UNKNOWN
Classifier: Development Status :: 2 - Pre-Alpha
Classifier: Intended Audience :: Developers
Classifier: Topic :: Education
Classifier: License :: OSI Approved :: GNU General Public License v3 (GPLv3)
Classifier: Programming Language :: Python :: 2
Classifier: Programming Language :: Python :: 3
Requires-Dist: spidev
